<Properties StartupConfiguration="{F4AAD932-546C-4111-964B-31EB3928517B}|Default">
  <MonoDevelop.Ide.ItemProperties.CounterAPI PreferredExecutionTarget="/Applications/Safari.app" />
  <MonoDevelop.Ide.Workbench ActiveDocument="CounterAPI/Models/CountedPeopleDatabaseSettings.cs">
    <Files>
      <File FileName="CounterAPI/Models/CountDay.cs" Line="9" Column="9" />
      <File FileName="CounterAPI/Startup.cs" Line="16" Column="1" />
      <File FileName="CounterAPI/appsettings.json" Line="16" Column="1" />
      <File FileName="CounterAPI/Models/CountedPeopleDatabaseSettings.cs" Line="6" Column="43" />
      <File FileName="CounterAPI/Controllers/CountedPeopleController.cs" />
      <File FileName="CounterAPI/Models/CountDayContext.cs" />
      <File FileName="CounterAPI/Services/CountedService.cs" />
    </Files>
    <Pads>
      <Pad Id="ProjectPad">
        <State name="__root__">
          <Node name="CounterAPI" expanded="True">
            <Node name="CounterAPI" expanded="True">
              <Node name="Controllers" expanded="True" />
              <Node name="Models" expanded="True">
                <Node name="CountedPeopleDatabaseSettings.cs" selected="True" />
              </Node>
              <Node name="Properties" expanded="True" />
              <Node name="Services" expanded="True" />
            </Node>
          </Node>
        </State>
      </Pad>
    </Pads>
  </MonoDevelop.Ide.Workbench>
  <MonoDevelop.Ide.DebuggingService.PinnedWatches />
  <MonoDevelop.Ide.Workspace ActiveConfiguration="Debug" />
  <MonoDevelop.Ide.DebuggingService.Breakpoints>
    <BreakpointStore />
  </MonoDevelop.Ide.DebuggingService.Breakpoints>
  <MultiItemStartupConfigurations />
</Properties>